timemap/__about__.py
timemap/__init__.py
timemap/__main__.py
timemap/error.py
timemap/event.py
timemap/report.py
timemap/timeline.py
timemap/utils.py
timemap/gmaps/__init__.py
timemap/gmaps/takeout.py
timemap-0.1.0.dist-info/LICENSE
timemap-0.1.0.dist-info/METADATA
timemap-0.1.0.dist-info/WHEEL
timemap-0.1.0.dist-info/top_level.txt
timemap-0.1.0.dist-info/RECORD
