Metadata-Version: 2.1
Name: timemap
Version: 0.1.0
Summary: Location history parser and analyzer.
Home-page: https://github.com/pfigs/location-history
Author: Pedro Silva
Author-email: noreply@pfgis.com
License: MIT
Keywords: maps location time tracking
Platform: UNKNOWN
Classifier: Development Status :: 4 - Beta
Classifier: Intended Audience :: Developers
Classifier: License :: OSI Approved :: Apache Software License
Classifier: Topic :: Software Development :: Libraries
Classifier: Programming Language :: Python :: 3
Requires-Dist: PyYAML (==5.1.2)
Requires-Dist: geopy (==1.20.0)
Requires-Dist: ijson (==2.4)
